{"files":{"packages/cli/dist/index.d.ts.map":{"size":133,"mtime_nanos":1775081119464652281,"mode":420,"is_dir":false},"packages/cli/dist/index.js":{"size":114,"mtime_nanos":1775081119460815943,"mode":420,"is_dir":false},"packages/cli/dist":{"size":0,"mtime_nanos":0,"mode":0,"is_dir":true},"packages/cli/.turbo/turbo-build.log":{"size":59,"mtime_nanos":1775081119495342986,"mode":420,"is_dir":false},"packages/cli/dist/index.js.map":{"size":154,"mtime_nanos":1775081119460815943,"mode":420,"is_dir":false},"packages/cli/dist/index.d.ts":{"size":75,"mtime_nanos":1775081119464652281,"mode":420,"is_dir":false}},"order":["packages/cli/.turbo/turbo-build.log","packages/cli/dist","packages/cli/dist/index.d.ts","packages/cli/dist/index.d.ts.map","packages/cli/dist/index.js","packages/cli/dist/index.js.map"]}